tensorflow_gan/__init__.py
tensorflow_gan/examples/__init__.py
tensorflow_gan/examples/compat_utils.py
tensorflow_gan/examples/evaluation_helper.py
tensorflow_gan/examples/evaluation_helper_test.py
tensorflow_gan/examples/cifar/__init__.py
tensorflow_gan/examples/cifar/data_provider.py
tensorflow_gan/examples/cifar/data_provider_test.py
tensorflow_gan/examples/cifar/eval.py
tensorflow_gan/examples/cifar/eval_lib.py
tensorflow_gan/examples/cifar/eval_test.py
tensorflow_gan/examples/cifar/networks.py
tensorflow_gan/examples/cifar/networks_test.py
tensorflow_gan/examples/cifar/train.py
tensorflow_gan/examples/cifar/train_lib.py
tensorflow_gan/examples/cifar/train_test.py
tensorflow_gan/examples/cifar/util.py
tensorflow_gan/examples/cifar/util_test.py
tensorflow_gan/examples/cyclegan/__init__.py
tensorflow_gan/examples/cyclegan/data_provider.py
tensorflow_gan/examples/cyclegan/data_provider_test.py
tensorflow_gan/examples/cyclegan/discriminator.py
tensorflow_gan/examples/cyclegan/discriminator_test.py
tensorflow_gan/examples/cyclegan/generator.py
tensorflow_gan/examples/cyclegan/generator_test.py
tensorflow_gan/examples/cyclegan/inference_demo.py
tensorflow_gan/examples/cyclegan/inference_demo_test.py
tensorflow_gan/examples/cyclegan/networks.py
tensorflow_gan/examples/cyclegan/networks_test.py
tensorflow_gan/examples/cyclegan/train.py
tensorflow_gan/examples/cyclegan/train_lib.py
tensorflow_gan/examples/cyclegan/train_test.py
tensorflow_gan/examples/mnist/__init__.py
tensorflow_gan/examples/mnist/conditional_eval.py
tensorflow_gan/examples/mnist/conditional_eval_lib.py
tensorflow_gan/examples/mnist/conditional_eval_test.py
tensorflow_gan/examples/mnist/data_provider.py
tensorflow_gan/examples/mnist/data_provider_test.py
tensorflow_gan/examples/mnist/eval.py
tensorflow_gan/examples/mnist/eval_lib.py
tensorflow_gan/examples/mnist/eval_test.py
tensorflow_gan/examples/mnist/infogan_eval.py
tensorflow_gan/examples/mnist/infogan_eval_lib.py
tensorflow_gan-2.1.0.dist-info/LICENSE
tensorflow_gan-2.1.0.dist-info/METADATA
tensorflow_gan-2.1.0.dist-info/WHEEL
tensorflow_gan-2.1.0.dist-info/top_level.txt
tensorflow_gan-2.1.0.dist-info/RECORD
